CHANGES.txt
Makefile
README.rst
setup.cfg
setup.py
buildout/__init__.py
buildout.packagename.egg-info/PKG-INFO
buildout.packagename.egg-info/SOURCES.txt
buildout.packagename.egg-info/dependency_links.txt
buildout.packagename.egg-info/entry_points.txt
buildout.packagename.egg-info/namespace_packages.txt
buildout.packagename.egg-info/requires.txt
buildout.packagename.egg-info/top_level.txt
buildout.packagename.egg-info/zip-safe
buildout/packagename/__init__.py
buildout/packagename/tests.py