Metadata-Version: 1.1
Name: buildout.packagename
Version: 1.0
Summary: A `zc.buildout` extension to extract the package name from an adjacent `setup.py`.
Home-page: https://github.com/witsch/buildout.packagename
Author: Andreas Zeidler
Author-email: witsch@plone.org
License: BSD
Keywords: buildout extension setuptools
Platform: UNKNOWN
Classifier: Framework :: Buildout
Classifier: Intended Audience :: Developers
Classifier: Topic :: Software Development :: Build Tools
Classifier: Topic :: Software Development :: Libraries :: Python Modules
